keyvec/__init__.py
keyvec/batch_text.py
keyvec/embed_chunk.py
keyvec/embed_store.py
keyvec/hf_model.py
keyvec-1.0.3.dist-info/LICENSE
keyvec-1.0.3.dist-info/METADATA
keyvec-1.0.3.dist-info/WHEEL
keyvec-1.0.3.dist-info/RECORD
