Metadata-Version: 2.1
Name: keyvec
Version: 1.0.3
Summary: For storing mapping from keys to vectors in your disk
License: MIT
Author: Binh Vu
Author-email: binh@toan2.com
Requires-Python: >=3.11,<4.0
Classifier: License :: OSI Approved :: MIT License
Classifier: Programming Language :: Python :: 3
Classifier: Programming Language :: Python :: 3.11
Classifier: Programming Language :: Python :: 3.12
Classifier: Programming Language :: Python :: 3.13
Requires-Dist: hugedict (>=2.14.0,<3.0.0)
Requires-Dist: numpy (>=2.1.1,<3.0.0)
Requires-Dist: ray (>=2.35.0,<3.0.0)
Requires-Dist: sem-desc (>=6.13.0,<7.0.0)
Requires-Dist: serde2 (>=1.8.3,<2.0.0)
